pyliturgical/__init__.py
pyliturgical/calendar.py
pyliturgical-1.0.1.dist-info/LICENSE
pyliturgical-1.0.1.dist-info/METADATA
pyliturgical-1.0.1.dist-info/WHEEL
pyliturgical-1.0.1.dist-info/top_level.txt
pyliturgical-1.0.1.dist-info/RECORD
